nonebot_plugin_anosu/__init__.py
nonebot_plugin_anosu-0.0.1.dist-info/LICENSE
nonebot_plugin_anosu-0.0.1.dist-info/METADATA
nonebot_plugin_anosu-0.0.1.dist-info/WHEEL
nonebot_plugin_anosu-0.0.1.dist-info/top_level.txt
nonebot_plugin_anosu-0.0.1.dist-info/RECORD
