Metadata-Version: 2.1
Name: nonebot-plugin-anosu
Version: 0.0.1
Summary: 接入image.anosu.top拿图的nonebot2色图插件
Home-page: https://github.com/KarisAya/nonebot_plugin_anosu
Author: karisaya
Author-email: 1048827424@qq.com
License: MIT license
Platform: all
License-File: LICENSE
Requires-Dist: nonebot2
Requires-Dist: nonebot-adapter-onebot
